README.md
setup.py
modeldiff/__init__.py
modeldiff/differ.py
modeldiff/pca.py
modeldiff.egg-info/PKG-INFO
modeldiff.egg-info/SOURCES.txt
modeldiff.egg-info/dependency_links.txt
modeldiff.egg-info/requires.txt
modeldiff.egg-info/top_level.txt