Metadata-Version: 2.1
Name: modeldiff
Version: 1.0.1
Summary: ModelDiff: A Framework for Comparing Learning Algorithms
Author: MadryLab
Author-email: harshay@mit.edu
Provides-Extra: notebooks
